{
	"info": {
		"_postman_id": "88364391-81e0-4a08-864f-45ff9f88586a",
		"name": "ReactChatProject",
		"schema": "https://schema.getpostman.com/json/collection/v2.1.0/collection.json",
		"_exporter_id": "30399592"
	},
	"item": [
		{
			"name": "User Controller",
			"item": [
				{
					"name": "createUser",
					"request": {
						"method": "POST",
						"header": [],
						"body": {
							"mode": "raw",
							"raw": "{\n    \"firstName\": \"John\",\n    \"lastName\": \"Wick\",\n    \"email\": \"jwick@puppyfinder.com\",\n    \"password\": \"focusCommitment1979\"\n}",
							"options": {
								"raw": {
									"language": "json"
								}
							}
						},
						"url": {
							"raw": "http://localhost:4000/user/createUser",
							"protocol": "http",
							"host": [
								"localhost"
							],
							"port": "4000",
							"path": [
								"user",
								"createUser"
							]
						}
					},
					"response": []
				},
				{
					"name": "signIn",
					"request": {
						"method": "POST",
						"header": [],
						"body": {
							"mode": "raw",
							"raw": "{\n    \"email\": \"jwick@puppyfinder.com\",\n    \"password\": \"focusCommitment1979\"\n}",
							"options": {
								"raw": {
									"language": "json"
								}
							}
						},
						"url": {
							"raw": "http://localhost:4000/user/login",
							"protocol": "http",
							"host": [
								"localhost"
							],
							"port": "4000",
							"path": [
								"user",
								"login"
							]
						}
					},
					"response": []
				}
			]
		},
		{
			"name": "Room Controller",
			"item": [
				{
					"name": "Create Room",
					"request": {
						"method": "POST",
						"header": [
							{
								"key": "Authorization",
								"value": "{{JWT}}",
								"type": "text"
							}
						],
						"body": {
							"mode": "raw",
							"raw": "{\n    \"name\": \"Continental\",\n    \"description\": \"No business conducted\",\n    \"addedUsers\": [\"John Wick\", \"Winston\", \"Ms. Perkins\"]\n}",
							"options": {
								"raw": {
									"language": "json"
								}
							}
						},
						"url": {
							"raw": "http://localhost:4000/room/createRoom",
							"protocol": "http",
							"host": [
								"localhost"
							],
							"port": "4000",
							"path": [
								"room",
								"createRoom"
							]
						}
					},
					"response": []
				}
			]
		}
	]
}